dooservice/__init__.py
dooservice/main.py
dooservice/backup/__init__.py
dooservice/backup/application/__init__.py
dooservice/backup/application/use_cases/__init__.py
dooservice/backup/application/use_cases/create_backup.py
dooservice/backup/application/use_cases/list_databases.py
dooservice/backup/application/use_cases/test_backup.py
dooservice/backup/domain/__init__.py
dooservice/backup/domain/entities/__init__.py
dooservice/backup/domain/entities/backup_configuration.py
dooservice/backup/domain/entities/backup_metadata.py
dooservice/backup/domain/exceptions/__init__.py
dooservice/backup/domain/exceptions/backup_exceptions.py
dooservice/backup/domain/repositories/__init__.py
dooservice/backup/domain/repositories/backup_configuration_repository.py
dooservice/backup/domain/services/__init__.py
dooservice/backup/domain/services/backup_executor.py
dooservice/backup/infrastructure/__init__.py
dooservice/backup/infrastructure/driven_adapter/__init__.py
dooservice/backup/infrastructure/driving_adapter/__init__.py
dooservice/backup/infrastructure/driving_adapter/cli/__init__.py
dooservice/backup/infrastructure/driving_adapter/cli/backup_cli.py
dooservice/backup/infrastructure/driving_adapter/cli/composer.py
dooservice/backup/infrastructure/driving_adapter/cli/main.py
dooservice/backup/infrastructure/implementation/__init__.py
dooservice/backup/infrastructure/implementation/xmlrpc_backup_executor.py
dooservice/core/__init__.py
dooservice/core/application/__init__.py
dooservice/core/application/use_cases/__init__.py
dooservice/core/application/use_cases/load_configuration.py
dooservice/core/application/use_cases/parse_yaml_configuration.py
dooservice/core/application/use_cases/save_configuration.py
dooservice/core/application/use_cases/validate_configuration.py
dooservice/core/domain/__init__.py
dooservice/core/domain/entities/__init__.py
dooservice/core/domain/entities/configuration.py
dooservice/core/domain/exceptions/__init__.py
dooservice_cli-0.13.0.dist-info/licenses/LICENSE
dooservice_cli-0.13.0.dist-info/METADATA
dooservice_cli-0.13.0.dist-info/WHEEL
dooservice_cli-0.13.0.dist-info/entry_points.txt
dooservice_cli-0.13.0.dist-info/top_level.txt
dooservice_cli-0.13.0.dist-info/RECORD
