Metadata-Version: 2.4
Name: dooservice-cli
Version: 0.13.0
Summary: Professional CLI tool for managing Odoo instances with declarative configuration, automated backups, snapshots, and GitHub integration.
Author-email: DooService Development Team <principal@apiservicesac.com>, API SERVICE SAC <principal@apiservicesac.com>
Maintainer-email: DooService Development Team <principal@apiservicesac.com>
License: MIT License
Project-URL: Homepage, https://apiservicesac.com
Project-URL: Documentation, https://github.com/apiservicesac/dooservice-cli-py#readme
Project-URL: Repository, https://github.com/apiservicesac/dooservice-cli-py
Project-URL: Issues, https://github.com/apiservicesac/dooservice-cli-py/issues
Project-URL: Changelog, https://github.com/apiservicesac/dooservice-cli-py/releases
Keywords: odoo,docker,cli,management,deployment,backup,snapshot,devops,automation,orchestration,containerization,enterprise,erp,github-integration,webhook,configuration-management
Classifier: Development Status :: 4 - Beta
Classifier: Intended Audience :: Developers
Classifier: Intended Audience :: System Administrators
Classifier: Intended Audience :: Information Technology
Classifier: License :: OSI Approved :: MIT License
Classifier: Operating System :: OS Independent
Classifier: Operating System :: POSIX :: Linux
Classifier: Operating System :: MacOS
Classifier: Operating System :: Microsoft :: Windows
Classifier: Programming Language :: Python :: 3
Classifier: Programming Language :: Python :: 3.9
Classifier: Programming Language :: Python :: 3.10
Classifier: Programming Language :: Python :: 3.11
Classifier: Programming Language :: Python :: 3.12
Classifier: Programming Language :: Python :: 3.13
Classifier: Programming Language :: Python :: Implementation :: CPython
Classifier: Topic :: Software Development :: Build Tools
Classifier: Topic :: Software Development :: Libraries :: Python Modules
Classifier: Topic :: System :: Systems Administration
Classifier: Topic :: System :: Installation/Setup
Classifier: Topic :: System :: Software Distribution
Classifier: Topic :: Database
Classifier: Topic :: Internet :: WWW/HTTP :: WSGI :: Application
Classifier: Environment :: Console
Classifier: Framework :: Odoo
Requires-Python: >=3.9
License-File: LICENSE
Requires-Dist: click>=8.0
Requires-Dist: pyyaml>=6.0
Requires-Dist: docker>=7.0.0
Requires-Dist: GitPython>=3.1
Requires-Dist: dacite>=1.6.0
Requires-Dist: toml>=0.10.2
Requires-Dist: requests>=2.25.0
Requires-Dist: cryptography>=3.0.0
Requires-Dist: psutil>=7.0.0
Requires-Dist: ruff>=0.11.13
Requires-Dist: httpx>=0.24.0
Requires-Dist: typer>=0.9.0
Requires-Dist: rich>=13.0.0
Requires-Dist: questionary>=2.1.1
Provides-Extra: dev
Requires-Dist: pytest>=7.0; extra == "dev"
Requires-Dist: flake8>=4.0; extra == "dev"
Requires-Dist: pytest-mock>=3.0; extra == "dev"
Requires-Dist: pytest-cov>=4.0; extra == "dev"
Requires-Dist: coverage>=7.0; extra == "dev"
Requires-Dist: ruff==0.11.13; extra == "dev"
Requires-Dist: build>=0.10.0; extra == "dev"
Requires-Dist: twine>=4.0.0; extra == "dev"
Dynamic: license-file
